huaweicloudsdkas/__init__.py
huaweicloudsdkas/v1/__init__.py
huaweicloudsdkas/v1/as_async_client.py
huaweicloudsdkas/v1/as_client.py
huaweicloudsdkas/v1/model/__init__.py
huaweicloudsdkas/v1/model/all_quotas.py
huaweicloudsdkas/v1/model/all_resources.py
huaweicloudsdkas/v1/model/allowed_address_pair.py
huaweicloudsdkas/v1/model/attach_callback_instance_life_cycle_hook_request.py
huaweicloudsdkas/v1/model/attach_callback_instance_life_cycle_hook_response.py
huaweicloudsdkas/v1/model/bandwidth_info.py
huaweicloudsdkas/v1/model/bandwidth_result.py
huaweicloudsdkas/v1/model/batch_add_instances_option.py
huaweicloudsdkas/v1/model/batch_add_scaling_instances_request.py
huaweicloudsdkas/v1/model/batch_add_scaling_instances_response.py
huaweicloudsdkas/v1/model/batch_delete_scaling_config_option.py
huaweicloudsdkas/v1/model/batch_delete_scaling_configs_request.py
huaweicloudsdkas/v1/model/batch_delete_scaling_configs_response.py
huaweicloudsdkas/v1/model/batch_delete_scaling_policies_option.py
huaweicloudsdkas/v1/model/batch_delete_scaling_policies_request.py
huaweicloudsdkas/v1/model/batch_delete_scaling_policies_response.py
huaweicloudsdkas/v1/model/batch_enter_standby_instances_option.py
huaweicloudsdkas/v1/model/batch_exit_stand_by_instances_option.py
huaweicloudsdkas/v1/model/batch_pause_scaling_policies_option.py
huaweicloudsdkas/v1/model/batch_pause_scaling_policies_request.py
huaweicloudsdkas/v1/model/batch_pause_scaling_policies_response.py
huaweicloudsdkas/v1/model/batch_protect_instances_option.py
huaweicloudsdkas/v1/model/batch_protect_scaling_instances_request.py
huaweicloudsdkas/v1/model/batch_protect_scaling_instances_response.py
huaweicloudsdkas/v1/model/batch_remove_instances_option.py
huaweicloudsdkas/v1/model/batch_remove_scaling_instances_request.py
huaweicloudsdkas/v1/model/batch_remove_scaling_instances_response.py
huaweicloudsdkas/v1/model/batch_resume_scaling_policies_option.py
huaweicloudsdkas/v1/model/batch_resume_scaling_policies_request.py
huaweicloudsdkas-3.1.184.dist-info/METADATA
huaweicloudsdkas-3.1.184.dist-info/WHEEL
huaweicloudsdkas-3.1.184.dist-info/licenses/LICENSE
huaweicloudsdkas-3.1.184.dist-info/RECORD
